community_explorer-0.1.0.dist-info/licenses/LICENSE
datasets/__init__.py
datasets/reactome.py
community_explorer-0.1.0.dist-info/METADATA
community_explorer-0.1.0.dist-info/WHEEL
community_explorer-0.1.0.dist-info/entry_points.txt
community_explorer-0.1.0.dist-info/top_level.txt
community_explorer-0.1.0.dist-info/RECORD
