Metadata-Version: 2.4
Name: community-explorer
Version: 0.1.0
Summary: A bioinformatics tool for network analysis and visualization of gene sets.
Author-email: Hugo Martiniano <hugomartiniano@gmail.com>
Project-URL: Homepage, https://github.com/hmartiniano/cx
Project-URL: Bug Tracker, https://github.com/hmartiniano/cx/issues
Classifier: Programming Language :: Python :: 3
Classifier: License :: OSI Approved :: MIT License
Classifier: Operating System :: OS Independent
Requires-Python: >=3.8
License-File: LICENSE
Requires-Dist: streamlit
Requires-Dist: pandas
Requires-Dist: typer
Requires-Dist: requests
Requires-Dist: numpy
Requires-Dist: networkx
Requires-Dist: cdlib
Requires-Dist: matplotlib
Requires-Dist: seaborn
Requires-Dist: gprofiler-official
Requires-Dist: scikit-learn
Provides-Extra: dev
Requires-Dist: pytest; extra == "dev"
Requires-Dist: flake8; extra == "dev"
Requires-Dist: black; extra == "dev"
Requires-Dist: build; extra == "dev"
Requires-Dist: isort; extra == "dev"
Requires-Dist: mypy; extra == "dev"
Requires-Dist: twine; extra == "dev"
Dynamic: license-file
